deepfit/DeepFit.py
deepfit/Main.py
deepfit/__init__.py
deepfit/demo.py
deepfitvlife-0.3.dist-info/DESCRIPTION.rst
deepfitvlife-0.3.dist-info/METADATA
deepfitvlife-0.3.dist-info/RECORD
deepfitvlife-0.3.dist-info/WHEEL
deepfitvlife-0.3.dist-info/metadata.json
deepfitvlife-0.3.dist-info/top_level.txt
