Metadata-Version: 2.0
Name: deepfitvlife
Version: 0.3
Summary: deepfit package
Home-page: https://github.com/Virtusa-vLife/deepfit
Author: Virtusa
Author-email: namagupta@virtusa.com
License: UNKNOWN
Platform: UNKNOWN
Classifier: Programming Language :: Python :: 3
Classifier: License :: OSI Approved :: MIT License
Classifier: Operating System :: OS Independent
